timer/__init__.py
timer/__main__.py
timer_cli-0.1.2.dist-info/LICENSE
timer_cli-0.1.2.dist-info/METADATA
timer_cli-0.1.2.dist-info/WHEEL
timer_cli-0.1.2.dist-info/entry_points.txt
timer_cli-0.1.2.dist-info/RECORD
