Metadata-Version: 2.1
Name: timer-cli
Version: 0.1.2
Summary: A simple CLI tool for starting a countdown timer.
Home-page: https://github.com/1Blademaster/timer-cli
License: Apache-2.0
Author: Kush Makkapati
Author-email: kush.makkapati@icloud.com
Requires-Python: >=3.7,<4.0
Classifier: License :: OSI Approved :: Apache Software License
Classifier: Programming Language :: Python :: 3
Classifier: Programming Language :: Python :: 3.7
Classifier: Programming Language :: Python :: 3.8
Classifier: Programming Language :: Python :: 3.9
Classifier: Programming Language :: Python :: 3.10
Classifier: Programming Language :: Python :: 3.11
Requires-Dist: art (>=5.9,<6.0)
Requires-Dist: click (>=8.1.3,<9.0.0)
Requires-Dist: rich (>=13.3.2,<14.0.0)
Project-URL: Repository, https://github.com/1Blademaster/timer-cli
